[
    {
        "key": "dbln",
        "value": "%7B%2261576947705878%22%3A%22m7ukQO9Y%22%2C%2261577886980259%22%3A%22VgRbzrF3%22%7D",
        "domain": "facebook.com",
        "path": "/login/device-based/",
        "hostOnly": false,
        "creation": "2025-06-26T12:07:08.077Z",
        "lastAccessed": "2025-06-26T12:07:08.077Z"
    },
    {
        "key": "datr",
        "value": "43JWaFKq9pYJhIEGesp8qNnU",
        "domain": "facebook.com",
        "path": "/",
        "hostOnly": false,
        "creation": "2025-06-26T12:07:08.077Z",
        "lastAccessed": "2025-06-26T12:07:08.077Z"
    },
    {
        "key": "sb",
        "value": "43JWaF1E3Q3KsXyElhCyHL9y",
        "domain": "facebook.com",
        "path": "/",
        "hostOnly": false,
        "creation": "2025-06-26T12:07:08.077Z",
        "lastAccessed": "2025-06-26T12:07:08.077Z"
    },
    {
        "key": "locale",
        "value": "en_GB",
        "domain": "facebook.com",
        "path": "/",
        "hostOnly": false,
        "creation": "2025-06-26T12:07:08.077Z",
        "lastAccessed": "2025-06-26T12:07:08.077Z"
    },
    {
        "key": "ps_l",
        "value": "1",
        "domain": "facebook.com",
        "path": "/",
        "hostOnly": false,
        "creation": "2025-06-26T12:07:08.077Z",
        "lastAccessed": "2025-06-26T12:07:08.077Z"
    },
    {
        "key": "ps_n",
        "value": "1",
        "domain": "facebook.com",
        "path": "/",
        "hostOnly": false,
        "creation": "2025-06-26T12:07:08.077Z",
        "lastAccessed": "2025-06-26T12:07:08.077Z"
    },
    {
        "key": "vpd",
        "value": "v1%3B799x424x2.294114351272583",
        "domain": "facebook.com",
        "path": "/",
        "hostOnly": false,
        "creation": "2025-06-26T12:07:08.077Z",
        "lastAccessed": "2025-06-26T12:07:08.077Z"
    },
    {
        "key": "dpr",
        "value": "2.294114351272583",
        "domain": "facebook.com",
        "path": "/",
        "hostOnly": false,
        "creation": "2025-06-26T12:07:08.077Z",
        "lastAccessed": "2025-06-26T12:07:08.077Z"
    },
    {
        "key": "c_user",
        "value": "61577886980259",
        "domain": "facebook.com",
        "path": "/",
        "hostOnly": false,
        "creation": "2025-06-26T12:07:08.077Z",
        "lastAccessed": "2025-06-26T12:07:08.077Z"
    },
    {
        "key": "xs",
        "value": "48%3AjC00aHVYrOXlew%3A2%3A1750505874%3A-1%3A-1",
        "domain": "facebook.com",
        "path": "/",
        "hostOnly": false,
        "creation": "2025-06-26T12:07:08.077Z",
        "lastAccessed": "2025-06-26T12:07:08.077Z"
    },
    {
        "key": "pas",
        "value": "61577886980259%3AYIO0En4RG9",
        "domain": "facebook.com",
        "path": "/",
        "hostOnly": false,
        "creation": "2025-06-26T12:07:08.077Z",
        "lastAccessed": "2025-06-26T12:07:08.077Z"
    },
    {
        "key": "fr",
        "value": "0aNCJF4qizB0FJdGj.AWeQenM1hPGrAJq7PAJwh2Gt9BBd0AoI9L5UVDnzLEXSFncXFVU.BoVnLj..AAA.0.0.BoXTfo.AWfYQoJusq2pTfcro6BPD7MLj-s",
        "domain": "facebook.com",
        "path": "/",
        "hostOnly": false,
        "creation": "2025-06-26T12:07:08.077Z",
        "lastAccessed": "2025-06-26T12:07:08.077Z"
    },
    {
        "key": "fbl_st",
        "value": "101028253%3BT%3A29182327",
        "domain": "facebook.com",
        "path": "/",
        "hostOnly": false,
        "creation": "2025-06-26T12:07:08.077Z",
        "lastAccessed": "2025-06-26T12:07:08.077Z"
    },
    {
        "key": "wl_cbv",
        "value": "v2%3Bclient_version%3A2854%3Btimestamp%3A1750939624",
        "domain": "facebook.com",
        "path": "/",
        "hostOnly": false,
        "creation": "2025-06-26T12:07:08.077Z",
        "lastAccessed": "2025-06-26T12:07:08.077Z"
    }
]
